aisUtils/Preprocessing.py
aisUtils/__init__.py
aisUtils-0.1.4.dist-info/LICENSE
aisUtils-0.1.4.dist-info/METADATA
aisUtils-0.1.4.dist-info/WHEEL
aisUtils-0.1.4.dist-info/top_level.txt
aisUtils-0.1.4.dist-info/RECORD
