Metadata-Version: 2.1
Name: aisUtils
Version: 0.1.4
Summary: ais tools package
Home-page: UNKNOWN
Author: mitscoder
Author-email: kongw@whut.edu.cn
License: UNKNOWN
Platform: UNKNOWN
Classifier: Programming Language :: Python :: 3
Classifier: License :: OSI Approved :: MIT License
Classifier: Operating System :: OS Independent
Requires-Python: >=3
License-File: LICENSE
Requires-Dist: retrying
Requires-Dist: requests
Requires-Dist: pandas
Requires-Dist: numpy
Requires-Dist: libais
